{"6CPYo5Kc15XX6V0d3FPMXQ==":"pr%C3%B3ba%202-2000x1334.png","ExwcB+JJSPpXS4Vf3eO9wg==":"pr%C3%B3ba%202-1183x789.png","qE+lpbQZbKh8gWCnqetfnQ==":"84138392_121889759182598_6717937885896507392_n-1280x1280.jpg","expEiqgq6Za1+SBiI1Qyhg==":"84138392_121889759182598_6717937885896507392_n-1280x1280.jpeg","1rE6N/4UjnjyicGyraGueQ==":"84138392_121889759182598_6717937885896507392_n-1-1280x1280.jpeg","fWiNCCNZPS94qV2LBZ6GDQ==":"84138392_121889759182598_6717937885896507392_n-2-1280x1280.jpeg","N0UPLnnguZi5dYkIgPPNug==":"kot-1-96x136.png","YqjbJxIYDxjfdOGSTMd2mQ==":"kot-2-96x136.png","ZYybPE6BB5b8BluhztCoRA==":"pr%C3%B3ba%202-2000x1334.png","Ci7Nw33Pzu59XGCty6kbfA==":"pr%C3%B3ba%202-edit-2000x1334.png","JwBGnO7G3d/wcsoC3JEW+Q==":"zetka1poziom%20(1%20of%201)-1920x1080.jpeg","MaIKUZL6F8t3E6yHSyue1g==":"zetka1poziom%20(1%20of%201)-816x459.jpeg","Wbi1WvK0Zgv2JOG3WIKjSg==":"driny%20(3%20of%204)-816x1224.jpeg","uDBPPYegUzSX1mY0jdcxwg==":"img-2148-816x1224.jpg","ke0/SGtiX+1GAGrJ+sb/Pg==":"img-2148-816x1224.jpeg","fThpr/85uvRgL3wrlYXI1g==":"img-2149-816x1224.jpeg","EbRwKtorvB2IhW7Vuy2C1w==":"range%20mar%20car%20(25%20of%2033)-1288x724.jpeg","MCN3sMACwHAXMypWkbDboQ==":"range%20mar%20car%20(18%20of%2033)-1288x1610.jpeg","ZlaxFowdQzTLxSZ1Aw95cw==":"range%20mar%20car%20(13%20of%2033)-1921x1082.jpg","Pxi6wrYWcMTw2dQp4hQBLA==":"m8%20(27%20of%2027)-3072x2048.jpg","3gJOqXt585plgjAcl0BQAg==":"m8%20(22%20of%2027)-3641x2048.jpg","QNaK7VKm1yNAQaMHbEEHYA==":"kia%20(1%20of%204)-1288x859.jpg","CXatNFyc1LCbbMeHfZkO8g==":"kiapion%20(6%20of%208)-1080x1620.jpg","Tr30k74NWJsOqrHJlQh2pg==":"%C5%9Awinialk%20(80%20of%205)-2800x3500.jpg","jP+V0j4Ca1mrGlbVlInYQw==":"golf%20(7%20of%2014)-5525x3108.jpg","xSafsN9+elSN8kEV8zgeiQ==":"golf%20(4%20of%2014)-6000x4000.jpg","nEnn5u+UN3OzHdeDUBoCpg==":"pors%20(3%20of%2018)-1080x1620.jpg","ztCfsQSD5Ve5tmK/SlmQ0A==":"mcbenzflatylampy%20(1%20of%2010)-1080x1350.jpg","xEU9GFFWe797Rh1Yd/tqMw==":"gtr%20(12%20of%2015)-2048x1152.jpg","Pkn/R3sYkHuq1qZXnKhRiA==":"gtr%20@@%20(1%20of%201)-2048x1152.jpg","EgX/CjAWfm0zW429bEwhmA==":"bmw%20bia%C5%82a%20%20(9%20of%2013)-900x1350.jpg","TxmFY2oEaekzTPLajdIutA==":"img-7127-2268x1080.jpg","7XwbL+btifgrVoX5pwOavA==":"img-6920-2268x1080.jpg","THOguX6j4+xrZ1ybjOUG7w==":"zetka1%20(1%20of%201)-1080x1350.jpg","hAOTPdOJ6Y46IcuzmiNpYw==":"audi%20a44%20poziom%20(5%20of%206)-1620x1080.jpg","MlE00Rc3Fr53BVPBUKqfSg==":"driny%20(3%20of%204)-900x1350.jpg","z0ytMgUXO9mEHdga5Hgu7w==":"img-7182-1175x783.jpg","QqZpMO/4QW1sPP2pZZe9nQ==":"img-7182-1175x783.jpeg","+tNZnO6atBqYB0FTA6eaBA==":"img-7183-1175x783.jpeg","DnYr+zySU9vA+dHsxIyIcA==":"img-7184-1175x783.jpg","FrO8WDZymGT186Hd+m2b5w==":"img-6707-900x1350.jpg","dZS3ePruFpzqS9H5HelgGQ==":"img-6699-900x1350.jpg","ydD96RTibAtaKVwfuVZfow==":"audi%20a44%20(6%20of%208)-900x1350.jpg","a5N/9QJtpFf5eApZA3haoQ==":"mcbenzflatylampy%20(4%20of%2010)-1080x1620.jpg","U+IpW9tQ757+rCs80jl5/g==":"img-8998-4000x6000.jpg","xOe/J9P1H7vcSwvnT+oFYg==":"img-9074-1256x1570.jpeg","b0HfaHZL6GNn+yeYl7yTtw==":"kia%20(1%20of%204)-1900x1267.jpg","OQsk8qS0/EIwLAf0t1ApjQ==":"m8%20(22%20of%2027)-1900x1069.jpg","O5MTQOXzQlfDxmS/I5OTlw==":"mazdunia%20lalunia%20%20(19%20of%2030)-1900x1069.jpg","wtz/OCHB5W0Sm9+08+CyAw==":"1%20(1%20of%201)-1900x1069.jpg","/oJzcXyxSMHk5DZ5p56yRQ==":"porstt%20(1%20of%2010)-1080x720.jpg","zYTXb9eaCVJih0m53Ulhxg==":"range%20mar%20car%20(13%20of%2033)-1080x608.jpg","8VFvFT4cmX/kU0r9fEywUA==":"range%20mar%20car%20(25%20of%2033)-1080x607.jpg","kxJhGMb4+XTFxN5pX5PKDA==":"range%20mar%20car%20(18%20of%2033)-1080x1350.jpg","vXSfCRJzZZKN/yp9k/vrAQ==":"skoda%20octavia%20(1%20of%2013)-1080x720.jpg","BYWCaAtaRCzNp7BrnrfHGw==":"skoda%20octavia%20(11%20of%2013)-1080x607.jpg","nBpQ2+/WbxS9kFtOjdUyNQ==":"skoda%20octavia%20(8%20of%2013)-2-1080x1350.jpg","EWIktVsf4nAH2pZGqcPXsg==":"audi%20qsq5%20(1%20of%203)-1080x463.jpg","W9/E0tWugDiJpLZLe85tGw==":"bmw%20bia%C5%82a%20pozim%20(1%20of%201)-720x1080.jpg","c2QNwoDs+NUXdjpL7nbIqQ==":"opel%20insygnia%20(5%20of%2015)-720x1080.jpg","qCcDF0MKz/1RUxlHe4HW1A==":"peugeot%20(15%20of%2016)-720x1080.jpg","0q9dUc0qLXbekV/lzN9C4Q==":"img-6920-720x343.jpg","poiF0HL8w8yfi6JU58xhkQ==":"img-7127-720x343.jpg","ML6fdpBqJ0v02R+KmHS/Mg==":"prba-2-edit.png"}